.gitignore
MANIFEST.in
README.rst
justfile
requirements-dev.txt
requirements-flake8.txt
requirements.txt
setup.py
template-version.txt
tox.ini
src/fhs_wireguard_namespace/__init__.py
src/fhs_wireguard_namespace/__version__.py
src/fhs_wireguard_namespace/cli.py
src/fhs_wireguard_namespace/create_wg_interface_in_namespace.py
src/fhs_wireguard_namespace/fhs_wireguard_namespace.py
src/fhs_wireguard_namespace/ip_wrapper.py
src/fhs_wireguard_namespace/network_configure_wireguard.py
src/fhs_wireguard_namespace/network_create_namespace.py
src/fhs_wireguard_namespace/network_create_wireguard.py
src/fhs_wireguard_namespace.egg-info/PKG-INFO
src/fhs_wireguard_namespace.egg-info/SOURCES.txt
src/fhs_wireguard_namespace.egg-info/dependency_links.txt
src/fhs_wireguard_namespace.egg-info/entry_points.txt
src/fhs_wireguard_namespace.egg-info/requires.txt
src/fhs_wireguard_namespace.egg-info/top_level.txt
tests/test_sample.py