Metadata-Version: 2.1
Name: fhs-wireguard-namespace
Version: 0.1.0
Summary: create a namespace with a wireguard interface for connectivity
Home-page: https://github.com/foxhunt72/fhs-wireguard-namespace
Author: Richard de Vos
Author-email: rdevos72@gmail.com
License: MIT license
Platform: UNKNOWN
Classifier: Development Status :: 4 - Beta
Classifier: Programming Language :: Python
Classifier: Programming Language :: Python :: 3
Classifier: Programming Language :: Python :: 3.6
Classifier: Programming Language :: Python :: 3.7
Classifier: Programming Language :: Python :: 3.8
Classifier: Programming Language :: Python :: 3.9
Classifier: Programming Language :: Python :: 3.10
